{"created_at": "Sun Jun 07 18:04:41 +0000 2020", "full_text": "ADA MF GREW LIKE A FINE WOMAN THAT SHE IS MMMMMMMMMMMMM TASTY", "hashtags": [], "id": 1269691765302284288, "id_str": "1269691765302284288", "in_reply_to_screen_name": "miseryrim", "in_reply_to_status_id": 1269691574155239425, "in_reply_to_user_id": 1156906589007126528, "lang": "en", "source": "<a href=\"https://mobile.twitter.com\" rel=\"nofollow\">Twitter Web App</a>", "urls": [], "user": {"id": 1156906589007126528, "id_str": "1156906589007126528"}, "user_mentions": [], "entities": {"hashtags": [], "symbols": [], "user_mentions": [], "urls": []}}