{"created_at": "Sat Jun 06 10:15:47 +0000 2020", "favorite_count": 4, "full_text": "BITCH U JUST NOTICED?????????????? https://t.co/NpPWLycDGN", "hashtags": [], "id": 1269211376846688259, "id_str": "1269211376846688259", "in_reply_to_screen_name": "miseryrim", "in_reply_to_status_id": 1269210993554452486, "in_reply_to_user_id": 1156906589007126528, "lang": "en", "media": [{"display_url": "pic.twitter.com/NpPWLycDGN", "expanded_url": "https://twitter.com/miseryrim/status/1269211376846688259/photo/1", "id": 1269211344676384769, "media_url": "http://pbs.twimg.com/media/EZ0k_lBU8AEpeKc.jpg", "media_url_https": "https://pbs.twimg.com/media/EZ0k_lBU8AEpeKc.jpg", "sizes": {"small": {"w": 680, "h": 382, "resize": "fit"}, "thumb": {"w": 150, "h": 150, "resize": "crop"}, "large": {"w": 1366, "h": 768, "resize": "fit"}, "medium": {"w": 1200, "h": 675, "resize": "fit"}}, "type": "photo", "url": "https://t.co/NpPWLycDGN"}], "retweet_count": 1, "source": "<a href=\"https://mobile.twitter.com\" rel=\"nofollow\">Twitter Web App</a>", "urls": [], "user": {"id": 1156906589007126528, "id_str": "1156906589007126528"}, "user_mentions": [], "entities": {"hashtags": [], "symbols": [], "user_mentions": [], "urls": [], "media": [{"id": 1269211344676384769, "id_str": "1269211344676384769", "indices": [35, 58], "media_url": "http://pbs.twimg.com/media/EZ0k_lBU8AEpeKc.jpg", "media_url_https": "https://pbs.twimg.com/media/EZ0k_lBU8AEpeKc.jpg", "url": "https://t.co/NpPWLycDGN", "display_url": "pic.twitter.com/NpPWLycDGN", "expanded_url": "https://twitter.com/miseryrim/status/1269211376846688259/photo/1", "type": "photo", "sizes": {"small": {"w": 680, "h": 382, "resize": "fit"}, "thumb": {"w": 150, "h": 150, "resize": "crop"}, "large": {"w": 1366, "h": 768, "resize": "fit"}, "medium": {"w": 1200, "h": 675, "resize": "fit"}}}]}, "extended_entities": {"media": [{"id": 1269211344676384769, "id_str": "1269211344676384769", "indices": [35, 58], "media_url": "http://pbs.twimg.com/media/EZ0k_lBU8AEpeKc.jpg", "media_url_https": "https://pbs.twimg.com/media/EZ0k_lBU8AEpeKc.jpg", "url": "https://t.co/NpPWLycDGN", "display_url": "pic.twitter.com/NpPWLycDGN", "expanded_url": "https://twitter.com/miseryrim/status/1269211376846688259/photo/1", "type": "photo", "sizes": {"small": {"w": 680, "h": 382, "resize": "fit"}, "thumb": {"w": 150, "h": 150, "resize": "crop"}, "large": {"w": 1366, "h": 768, "resize": "fit"}, "medium": {"w": 1200, "h": 675, "resize": "fit"}}, "ext_alt_text": null}]}}