{"created_at": "Wed Jun 10 01:15:29 +0000 2020", "full_text": "@KumikosEupho You broke it for me too you idiot", "hashtags": [], "id": 1270524957806735360, "id_str": "1270524957806735360", "in_reply_to_screen_name": "KumikosEupho", "in_reply_to_status_id": 1270524817675112448, "in_reply_to_user_id": 1218714924572127233, "lang": "en", "source": "<a href=\"http://twitter.com/download/android\" rel=\"nofollow\">Twitter for Android</a>", "urls": [], "user": {"id": 1143372058354683905, "id_str": "1143372058354683905"}, "user_mentions": [{"id": 1218714924572127233, "id_str": "1218714924572127233", "name": "Chonko \ud83c\udf38", "screen_name": "KumikosEupho"}], "entities": {"hashtags": [], "symbols": [], "user_mentions": [{"screen_name": "KumikosEupho", "name": "Chonko \ud83c\udf38", "id": 1218714924572127233, "id_str": "1218714924572127233", "indices": [0, 13]}], "urls": []}}