{"created_at": "Sun Mar 26 00:48:03 +0000 2006", "favorite_count": 162, "full_text": "noting that you guys are in the same places (ev&jack) planning to do the same things (ev&biz) or thinking the same things (noah&ev) or were all just together...", "hashtags": [], "id": 359, "id_str": "359", "lang": "en", "retweet_count": 212, "source": "<a href=\"http://twitter.com\" rel=\"nofollow\">Twitter Web Client</a>", "urls": [], "user": {"id": 15, "id_str": "15"}, "user_mentions": [], "entities": {"hashtags": [], "symbols": [], "user_mentions": [], "urls": []}}