{"created_at": "Sun Jan 15 04:23:17 +0000 2012", "description": "Vocalist | Mixer | Food Safety Specialist/Inspector | PenguinMafia Bossman | Amateur Barista | Collabs: OPEN | Commission: OPEN https://t.co/vHAlaOvzsi", "favourites_count": 22651, "followers_count": 2340, "friends_count": 467, "geo_enabled": true, "id": 464357641, "id_str": "464357641", "listed_count": 9, "location": "Hawaii", "name": "Jefferz @ Mix Comms (OPEN)", "profile_background_color": "022330", "profile_background_image_url": "http://abs.twimg.com/images/themes/theme15/bg.png", "profile_background_image_url_https": "https://abs.twimg.com/images/themes/theme15/bg.png", "profile_banner_url": "https://pbs.twimg.com/profile_banners/464357641/1525572637", "profile_image_url": "http://pbs.twimg.com/profile_images/729034114486013952/WFWV5Sl-_normal.jpg", "profile_image_url_https": "https://pbs.twimg.com/profile_images/729034114486013952/WFWV5Sl-_normal.jpg", "profile_link_color": "0084B4", "profile_sidebar_border_color": "A8C7F7", "profile_sidebar_fill_color": "C0DFEC", "profile_text_color": "333333", "profile_use_background_image": true, "screen_name": "Jefferzkm", "status": {"created_at": "Tue Jun 09 02:47:52 +0000 2020", "full_text": "RT @siahyuk: I covered #GrandEscape from #WeatheringWithYou \n\nspecial thanks to all the singers for the chorus part!\n@Ezawin @hakeruuu @Jef\u2026", "hashtags": [{"text": "GrandEscape"}, {"text": "WeatheringWithYou"}], "id": 1270185815612637184, "id_str": "1270185815612637184", "lang": "en", "retweet_count": 26, "retweeted_status": {"created_at": "Tue Jun 09 02:32:17 +0000 2020", "favorite_count": 47, "full_text": "I covered #GrandEscape from #WeatheringWithYou \n\nspecial thanks to all the singers for the chorus part!\n@Ezawin @hakeruuu @Jefferzkm @Jordy905 @vhinar @ariadneblnchflr @waterpixieva @xMarinePearlx @LunaAmatista \n\nYT: https://t.co/HgQjFOc9gr\n\n(RT's appreciated!) \u2282(\u00b4\u2022 \u03c9 \u2022`\u2282) https://t.co/C5LpMQ5jRD", "hashtags": [{"text": "GrandEscape"}, {"text": "WeatheringWithYou"}], "id": 1270181895620505603, "id_str": "1270181895620505603", "lang": "en", "media": [{"display_url": "pic.twitter.com/C5LpMQ5jRD", "expanded_url": "https://twitter.com/siahyuk/status/1270181895620505603/video/1", "id": 1270180668299935744, "media_url": "http://pbs.twimg.com/ext_tw_video_thumb/1270180668299935744/pu/img/JWZZ9IpAJquiGBQp.jpg", "media_url_https": "https://pbs.twimg.com/ext_tw_video_thumb/1270180668299935744/pu/img/JWZZ9IpAJquiGBQp.jpg", "sizes": {"thumb": {"w": 150, "h": 150, "resize": "crop"}, "medium": {"w": 1200, "h": 675, "resize": "fit"}, "small": {"w": 680, "h": 383, "resize": "fit"}, "large": {"w": 1280, "h": 720, "resize": "fit"}}, "type": "video", "url": "https://t.co/C5LpMQ5jRD", "video_info": {"aspect_ratio": [16, 9], "duration_millis": 82209, "variants": [{"bitrate": 832000, "content_type": "video/mp4", "url": "https://video.twimg.com/ext_tw_video/1270180668299935744/pu/vid/640x360/6VhykwKc7f-oLoCo.mp4?tag=10"}, {"bitrate": 2176000, "content_type": "video/mp4", "url": "https://video.twimg.com/ext_tw_video/1270180668299935744/pu/vid/1280x720/fLcDZuM_KLCfcwNb.mp4?tag=10"}, {"content_type": "application/x-mpegURL", "url": "https://video.twimg.com/ext_tw_video/1270180668299935744/pu/pl/MZUET2Y0k-vfHmu-.m3u8?tag=10"}, {"bitrate": 256000, "content_type": "video/mp4", "url": "https://video.twimg.com/ext_tw_video/1270180668299935744/pu/vid/480x270/Gf2HggrH3LkQZoqS.mp4?tag=10"}]}}], "retweet_count": 26, "source": "<a href=\"https://mobile.twitter.com\" rel=\"nofollow\">Twitter Web App</a>", "urls": [{"expanded_url": "https://youtu.be/wCE2PJE-POE", "url": "https://t.co/HgQjFOc9gr"}], "user_mentions": [{"id": 720901501, "id_str": "720901501", "name": "Wind", "screen_name": "Ezawin"}, {"id": 105481350, "id_str": "105481350", "name": "Hakeru", "screen_name": "hakeruuu"}, {"id": 464357641, "id_str": "464357641", "name": "Jefferz @ Mix Comms (OPEN)", "screen_name": "Jefferzkm"}, {"id": 306926489, "id_str": "306926489", "name": "Jordy", "screen_name": "Jordy905"}, {"id": 128964968, "id_str": "128964968", "name": "Vinar Takumi", "screen_name": "vhinar"}, {"id": 3303627506, "id_str": "3303627506", "name": "pwb@Pandora-MSCB | COMMS OPEN", "screen_name": "ariadneblnchflr"}, {"id": 234286799, "id_str": "234286799", "name": "Eva \u2756 CODEX // Gemini", "screen_name": "waterpixieva"}, {"id": 384472585, "id_str": "384472585", "name": "Matti\u2b50\ufe0f", "screen_name": "xMarinePearlx"}, {"id": 37726380, "id_str": "37726380", "name": "\ud83c\udf19", "screen_name": "LunaAmatista"}]}, "source": "<a href=\"https://about.twitter.com/products/tweetdeck\" rel=\"nofollow\">TweetDeck</a>", "urls": [], "user_mentions": [{"id": 237016828, "id_str": "237016828", "name": "S i A | not Fujoshi \ud83d\udd1e", "screen_name": "siahyuk"}, {"id": 720901501, "id_str": "720901501", "name": "Wind", "screen_name": "Ezawin"}, {"id": 105481350, "id_str": "105481350", "name": "Hakeru", "screen_name": "hakeruuu"}]}, "statuses_count": 32600, "url": "https://t.co/msNNkNa5Mw", "entities": {"url": {"urls": [{"url": "https://t.co/msNNkNa5Mw", "expanded_url": "http://www.youtube.com/jefferzkm", "display_url": "youtube.com/jefferzkm", "indices": [0, 23]}]}, "description": {"urls": [{"url": "https://t.co/vHAlaOvzsi", "expanded_url": "http://jefferzkm.com/commissions", "display_url": "jefferzkm.com/commissions", "indices": [128, 151]}]}}}